flet/__init__.py
flet/auth/__init__.py
flet/auth/providers/__init__.py
flet/canvas/__init__.py
flet/matplotlib_chart.py
flet/plotly_chart.py
flet/security/__init__.py
flet/utils/__init__.py
flet/version.py
flet_contrib_embed-2024.12.7.2153.dist-info/METADATA
flet_contrib_embed-2024.12.7.2153.dist-info/WHEEL
flet_contrib_embed-2024.12.7.2153.dist-info/RECORD
